pyGenieScript/__init__.py
pyGenieScript/geniescript.py
pyGenieScript/package.json
pyGenieScript/tests/__init__.py
pyGenieScript/tests/test_setup.py
pyGenieScript-0.0.0b20.dist-info/LICENSE
pyGenieScript-0.0.0b20.dist-info/METADATA
pyGenieScript-0.0.0b20.dist-info/WHEEL
pyGenieScript-0.0.0b20.dist-info/top_level.txt
pyGenieScript-0.0.0b20.dist-info/RECORD
