Metadata-Version: 2.1
Name: pyGenieScript
Version: 0.0.0b20
Summary: A packaged GenieScript in Python
Author: Stanford University Open Virtual Assistant Lab
Author-email: Shicheng Liu <shicheng@cs.stanford.edu>
Project-URL: Homepage, https://github.com/stanford-oval/pyGenieScript.git
Classifier: Programming Language :: Python :: 3
Classifier: License :: OSI Approved :: MIT License
Classifier: Operating System :: OS Independent
Requires-Python: >=3.7
License-File: LICENSE
Requires-Dist: huggingface-hub (>=0.12.0)
Requires-Dist: pdoc (>=12.3.1)
